{
  "_comment": "Scenario: oscillating coolant slope that triggers, drops below hysteresis, then re-triggers. Tests TrustEngine hysteresis and cooldown interaction. Pattern: slope rises fast (fires coolant_rising_fast), then drops to barely-above-threshold (suppressed by hysteresis on re-fire), then spikes sharply again (passes hysteresis). cooldown_ms=20000 for coolant_rising_fast.",
  "name": "oscillating_fault",
  "vehicle_class": "LIGHT_TRUCK",
  "asset_id": "SIM-004",
  "driver_id": "DRV-SIM",
  "expected_alerts": ["coolant_rising_fast"],
  "expected_max_severity": "CRITICAL",
  "frames": [
    { "ts_offset_ms": 0, "signals": { "coolant_temp": 85.0, "engine_rpm": 2200, "vehicle_speed": 80 } },
    { "ts_offset_ms":  1000, "signals": { "coolant_temp": 85.0, "engine_rpm": 2200, "vehicle_speed": 80 } },
    { "ts_offset_ms":  2000, "signals": { "coolant_temp": 85.0, "engine_rpm": 2200, "vehicle_speed": 80 } },
    { "ts_offset_ms":  3000, "signals": { "coolant_temp": 85.0, "engine_rpm": 2200, "vehicle_speed": 80 } },
    { "ts_offset_ms":  4000, "signals": { "coolant_temp": 85.0, "engine_rpm": 2200, "vehicle_speed": 80 } },
    { "ts_offset_ms":  5000, "signals": { "coolant_temp": 85.0, "engine_rpm": 2200, "vehicle_speed": 80 } },
    { "ts_offset_ms":  6000, "signals": { "coolant_temp": 85.0, "engine_rpm": 2200, "vehicle_speed": 80 } },
    { "ts_offset_ms":  7000, "signals": { "coolant_temp": 85.0, "engine_rpm": 2200, "vehicle_speed": 80 } },
    { "ts_offset_ms":  8000, "signals": { "coolant_temp": 85.0, "engine_rpm": 2200, "vehicle_speed": 80 } },
    { "ts_offset_ms":  9000, "signals": { "coolant_temp": 85.0, "engine_rpm": 2200, "vehicle_speed": 80 } },
    { "ts_offset_ms": 10000, "signals": { "coolant_temp": 130.0, "engine_rpm": 2300, "vehicle_speed": 80 } },
    { "ts_offset_ms": 11000, "signals": { "coolant_temp": 131.0, "engine_rpm": 2300, "vehicle_speed": 80 } },
    { "ts_offset_ms": 12000, "signals": { "coolant_temp": 132.0, "engine_rpm": 2300, "vehicle_speed": 80 } },
    { "ts_offset_ms": 13000, "signals": { "coolant_temp": 133.0, "engine_rpm": 2300, "vehicle_speed": 80 } },
    { "ts_offset_ms": 14000, "signals": { "coolant_temp": 134.0, "engine_rpm": 2300, "vehicle_speed": 80 } },
    { "ts_offset_ms": 15000, "signals": { "coolant_temp": 135.0, "engine_rpm": 2300, "vehicle_speed": 80 } },
    { "ts_offset_ms": 16000, "signals": { "coolant_temp": 136.0, "engine_rpm": 2300, "vehicle_speed": 80 } },
    { "ts_offset_ms": 17000, "signals": { "coolant_temp": 137.0, "engine_rpm": 2300, "vehicle_speed": 80 } },
    { "ts_offset_ms": 18000, "signals": { "coolant_temp": 138.0, "engine_rpm": 2300, "vehicle_speed": 80 } },
    { "ts_offset_ms": 19000, "signals": { "coolant_temp": 139.0, "engine_rpm": 2300, "vehicle_speed": 80 } },
    { "ts_offset_ms": 20000, "signals": { "coolant_temp": 138.5, "engine_rpm": 2250, "vehicle_speed": 80 } },
    { "ts_offset_ms": 21000, "signals": { "coolant_temp": 138.0, "engine_rpm": 2250, "vehicle_speed": 80 } },
    { "ts_offset_ms": 22000, "signals": { "coolant_temp": 137.5, "engine_rpm": 2250, "vehicle_speed": 80 } },
    { "ts_offset_ms": 23000, "signals": { "coolant_temp": 137.0, "engine_rpm": 2250, "vehicle_speed": 80 } },
    { "ts_offset_ms": 24000, "signals": { "coolant_temp": 136.5, "engine_rpm": 2250, "vehicle_speed": 80 } },
    { "ts_offset_ms": 25000, "signals": { "coolant_temp": 136.0, "engine_rpm": 2250, "vehicle_speed": 80 } },
    { "ts_offset_ms": 26000, "signals": { "coolant_temp": 135.5, "engine_rpm": 2250, "vehicle_speed": 80 } },
    { "ts_offset_ms": 27000, "signals": { "coolant_temp": 135.0, "engine_rpm": 2250, "vehicle_speed": 80 } },
    { "ts_offset_ms": 28000, "signals": { "coolant_temp": 134.5, "engine_rpm": 2250, "vehicle_speed": 80 } },
    { "ts_offset_ms": 29000, "signals": { "coolant_temp": 134.0, "engine_rpm": 2250, "vehicle_speed": 80 } },
    { "ts_offset_ms": 30000, "signals": { "coolant_temp": 133.5, "engine_rpm": 2250, "vehicle_speed": 80 } },
    { "ts_offset_ms": 31000, "signals": { "coolant_temp": 133.5, "engine_rpm": 2200, "vehicle_speed": 80 } },
    { "ts_offset_ms": 32000, "signals": { "coolant_temp": 133.5, "engine_rpm": 2200, "vehicle_speed": 80 } },
    { "ts_offset_ms": 33000, "signals": { "coolant_temp": 133.5, "engine_rpm": 2200, "vehicle_speed": 80 } },
    { "ts_offset_ms": 34000, "signals": { "coolant_temp": 133.5, "engine_rpm": 2200, "vehicle_speed": 80 } },
    { "ts_offset_ms": 35000, "signals": { "coolant_temp": 133.5, "engine_rpm": 2200, "vehicle_speed": 80 } },
    { "ts_offset_ms": 36000, "signals": { "coolant_temp": 133.5, "engine_rpm": 2200, "vehicle_speed": 80 } },
    { "ts_offset_ms": 37000, "signals": { "coolant_temp": 133.5, "engine_rpm": 2200, "vehicle_speed": 80 } },
    { "ts_offset_ms": 38000, "signals": { "coolant_temp": 133.5, "engine_rpm": 2200, "vehicle_speed": 80 } },
    { "ts_offset_ms": 39000, "signals": { "coolant_temp": 133.5, "engine_rpm": 2200, "vehicle_speed": 80 } },
    { "ts_offset_ms": 40000, "signals": { "coolant_temp": 133.5, "engine_rpm": 2200, "vehicle_speed": 80 } },
    { "ts_offset_ms": 50000, "signals": { "coolant_temp": 133.5, "engine_rpm": 2200, "vehicle_speed": 80 } },
    { "ts_offset_ms": 51000, "signals": { "coolant_temp": 133.5, "engine_rpm": 2200, "vehicle_speed": 80 } },
    { "ts_offset_ms": 52000, "signals": { "coolant_temp": 133.5, "engine_rpm": 2200, "vehicle_speed": 80 } },
    { "ts_offset_ms": 53000, "signals": { "coolant_temp": 133.5, "engine_rpm": 2200, "vehicle_speed": 80 } },
    { "ts_offset_ms": 54000, "signals": { "coolant_temp": 133.5, "engine_rpm": 2200, "vehicle_speed": 80 } },
    { "ts_offset_ms": 55000, "signals": { "coolant_temp": 133.5, "engine_rpm": 2200, "vehicle_speed": 80 } },
    { "ts_offset_ms": 56000, "signals": { "coolant_temp": 133.5, "engine_rpm": 2200, "vehicle_speed": 80 } },
    { "ts_offset_ms": 57000, "signals": { "coolant_temp": 133.5, "engine_rpm": 2200, "vehicle_speed": 80 } },
    { "ts_offset_ms": 58000, "signals": { "coolant_temp": 133.5, "engine_rpm": 2200, "vehicle_speed": 80 } },
    { "ts_offset_ms": 59000, "signals": { "coolant_temp": 165.0, "engine_rpm": 2400, "vehicle_speed": 80 } }
  ]
}
